<?xml version="1.0" encoding="UTF-8"?>
<schemalist>
  <schema id="org.gnome.shell.extensions.focus-guard"
          path="/org/gnome/shell/extensions/focus-guard/">
    <key name="blocked-apps" type="as">
      <default>[]</default>
      <summary>Blocked application IDs</summary>
      <description>List of application desktop IDs that are blocked. Format: "app.id.desktop|App Name"</description>
    </key>
    <key name="last-blocked-apps" type="as">
      <default>[]</default>
      <summary>Last blocked application IDs</summary>
      <description>Snapshot of blocked apps saved when "Unblock all" is used, so the list can be restored.</description>
    </key>
    <key name="blocking-enabled" type="b">
      <default>true</default>
      <summary>Blocking enabled</summary>
      <description>Whether app blocking is currently active. When false, the blocked apps list is preserved but no windows are minimized.</description>
    </key>
    <key name="toggle-shortcut" type="as">
      <default>[]</default>
      <summary>Toggle shortcut</summary>
      <description>Keyboard shortcut to toggle app blocking on/off.</description>
    </key>
  </schema>
</schemalist>
